.gitignore
CHANGES.txt
CONTRIBUTORS.txt
MANIFEST.in
README.rst
README.txt
setup.cfg
setup.py
docs/LICENSE.GPL
docs/LICENSE.txt
docs/devnotes.txt
src/collective/__init__.py
src/collective.traceview.egg-info/PKG-INFO
src/collective.traceview.egg-info/SOURCES.txt
src/collective.traceview.egg-info/dependency_links.txt
src/collective.traceview.egg-info/entry_points.txt
src/collective.traceview.egg-info/namespace_packages.txt
src/collective.traceview.egg-info/not-zip-safe
src/collective.traceview.egg-info/requires.txt
src/collective.traceview.egg-info/top_level.txt
src/collective/traceview/__init__.py
src/collective/traceview/configure.zcml
src/collective/traceview/interfaces.py
src/collective/traceview/view.py
src/collective/traceview/patches/__init__.py
src/collective/traceview/patches/catalog.py
src/collective/traceview/patches/chameleonpatch.py
src/collective/traceview/patches/httpserver.py
src/collective/traceview/patches/memoize.py
src/collective/traceview/patches/oboeexception.py
src/collective/traceview/patches/publisher.py
src/collective/traceview/patches/templates.py
src/collective/traceview/patches/transform.py
src/collective/traceview/patches/traversepatch.py
src/collective/traceview/patches/viewletmanagers.py
src/collective/traceview/patches/zodbpatch.py
src/collective/traceview/profiles/default/browserlayer.xml
src/collective/traceview/profiles/default/viewlets.xml