Metadata-Version: 1.1
Name: collective.traceview
Version: 1.4
Summary: This package adds support for TraceView performance instrumentation in Plone
Home-page: https://github.com/collective/collective.traceview
Author: Anton Stonor
Author-email: anton@headnet.dk
License: GPL
Keywords: collective traceview tracelytics
Platform: UNKNOWN
Classifier: Environment :: Web Environment
Classifier: Framework :: Plone
Classifier: Operating System :: OS Independent
Classifier: Programming Language :: Python
Classifier: Programming Language :: Python :: 2.6
Classifier: Topic :: Software Development :: Libraries :: Python Modules
Classifier: License :: OSI Approved :: GNU General Public License (GPL)
